procsight/__init__.py
procsight/cli/__init__.py
procsight/cli/parser.py
procsight/core/__init__.py
procsight/core/file_export.py
procsight/core/monitor.py
procsight/core/sample_collector.py
procsight/models/__init__.py
procsight/models/metrics.py
procsight/visualization/__init__.py
procsight/visualization/plot.py
procsight/visualization/style.py
procsight-1.0.0.dist-info/LICENSE
procsight-1.0.0.dist-info/METADATA
procsight-1.0.0.dist-info/WHEEL
procsight-1.0.0.dist-info/RECORD
