Metadata-Version: 2.1
Name: procsight
Version: 1.0.0
Summary: Python tool for monitoring and visualizing a running processes usage
License: MIT
Author: ErikDoytchinov
Author-email: erik.doytchinov@gmail.com
Requires-Python: >=3.11,<4.0
Classifier: License :: OSI Approved :: MIT License
Classifier: Programming Language :: Python :: 3
Classifier: Programming Language :: Python :: 3.11
Classifier: Programming Language :: Python :: 3.12
Requires-Dist: keyboard (>=0.13.5,<0.14.0)
Requires-Dist: loguru (>=0.7.3,<0.8.0)
Requires-Dist: matplotlib (>=3.10.3,<4.0.0)
Requires-Dist: pandas (>=2.3.0,<3.0.0)
Requires-Dist: psutil (>=7.0.0,<8.0.0)
Requires-Dist: pydantic (>=2.11.7,<3.0.0)
Requires-Dist: ruff (>=0.12.2,<0.13.0)
Requires-Dist: schedule (>=1.2.2,<2.0.0)
Requires-Dist: seaborn (>=0.13.2,<0.14.0)
